Metadata-Version: 1.1
Name: PycordLib
Version: 1.3.0
Summary: Simple Discord bot library
Home-page: https://github.com/Celeo/Pycord
Author: Matt Boulanger
Author-email: celeodor@gmail.com
License: MIT
Keywords: discord
Platform: any
Classifier: Environment :: Console
Classifier: Environment :: Web Environment
Classifier: Operating System :: OS Independent
Classifier: Programming Language :: Python :: 3
Classifier: Topic :: Software Development :: Libraries
